swrapper/__init__.py
swrapper/__main__.py
swrapper/exceptions.py
swrapper/wargs.py
swrapper/wconfig.py
swrapper/wlog.py
py_script_wrapper-0.2.1.dist-info/LICENSE
py_script_wrapper-0.2.1.dist-info/METADATA
py_script_wrapper-0.2.1.dist-info/WHEEL
py_script_wrapper-0.2.1.dist-info/top_level.txt
py_script_wrapper-0.2.1.dist-info/RECORD
