Metadata-Version: 2.1
Name: py-script-wrapper
Version: 0.2.1
Summary: A simple wrapper for the py-scripts
Author: Majorant
Maintainer-email: Majorant <Majorant@users.noreply.github.com>
License: Apache License
Project-URL: Homepage, https://github.com/Majorant/py-script-wrapper
Project-URL: Issues, https://github.com/Majorant/py-script-wrapper/issues
Classifier: Programming Language :: Python :: 3
Classifier: License :: OSI Approved :: Apache Software License
Classifier: Operating System :: OS Independent
Requires-Python: >=3.8
License-File: LICENSE
Requires-Dist: simplejson >=3.16.0
Requires-Dist: PyYAML >=5.3.1
